pachelm/__init__.py
pachelm/cli.py
pachelm/core.py
pachelm/migration.py
pachelm/utils.py
pachelm-0.0.26.data/scripts/pachelm
tests/__init__.py
tests/conftest.py
tests/integration_test.py
tests/test_core.py
tests/test_migrate.py
tests/test_utils.py
pachelm-0.0.26.dist-info/LICENSE
pachelm-0.0.26.dist-info/METADATA
pachelm-0.0.26.dist-info/WHEEL
pachelm-0.0.26.dist-info/top_level.txt
pachelm-0.0.26.dist-info/RECORD
